Metadata-Version: 2.1
Name: hibro
Version: 0.2.1
Summary: Standalone history browser for Home Assistant
Home-page: https://github.com/DavidMStraub/HiBro
Author: David Straub
Author-email: straub@protonmail.com
License: UNKNOWN
Keywords: hibro
Platform: UNKNOWN
Requires-Python: >=3.6
